README.rst
sdc-tool
setup.cfg
setup.py
sdctool/__init__.py
sdctool/api.py
sdctool/commands.py
sdctool/conf.py
sdctool/sdc_tool.py
sdctool.egg-info/PKG-INFO
sdctool.egg-info/SOURCES.txt
sdctool.egg-info/dependency_links.txt
sdctool.egg-info/requires.txt
sdctool.egg-info/top_level.txt
test/test_import.py
test/test_start_stop.py
test/test_validate.py