Metadata-Version: 1.1
Name: sdctool
Version: 0.11.0
Summary: Streamsets DataCollector API utility
Home-page: https://github.com/phdata/sdc-api-tool
Author: phData inc
Author-email: brian@phdata.io, tony@phdata.io
License: UNKNOWN
Download-URL: https://github.com/phdata/sdc-api-tool/tree/master/dist/sdc-tool-0.11.0.tar.gz
Keywords: streamsets,api,pipeline,cli
Platform: UNKNOWN
